streamlit_dsfr/__init__.py
streamlit_dsfr/override_font_family.py
streamlit_dsfr/frontend/st_dsfr_alert/index.html
streamlit_dsfr/frontend/st_dsfr_badge/index.html
streamlit_dsfr/frontend/st_dsfr_breadcrumb/index.html
streamlit_dsfr/frontend/st_dsfr_button/index.html
streamlit_dsfr/frontend/st_dsfr_buttons_group/index.html
streamlit_dsfr/frontend/st_dsfr_checkbox/index.html
streamlit_dsfr/frontend/st_dsfr_default/index.html
streamlit_dsfr/frontend/st_dsfr_default/_astro/DsfrAlert.Cg-dfeRQ.js
streamlit_dsfr/frontend/st_dsfr_default/_astro/DsfrBadge.B_gjrR3R.js
streamlit_dsfr/frontend/st_dsfr_default/_astro/DsfrBreadcrumb.B8uzIOr2.js
streamlit_dsfr/frontend/st_dsfr_default/_astro/DsfrButton.CPUMiqz6.js
streamlit_dsfr/frontend/st_dsfr_default/_astro/DsfrButton.DpDkSSeL.js
streamlit_dsfr/frontend/st_dsfr_default/_astro/DsfrButtonGroup.CeAwjfau.js
streamlit_dsfr/frontend/st_dsfr_default/_astro/DsfrCheckbox.CpRD10NZ.js
streamlit_dsfr/frontend/st_dsfr_default/_astro/DsfrFileUpload.6nxBNMf0.js
streamlit_dsfr/frontend/st_dsfr_default/_astro/DsfrFooter.Cd77QhIw.js
streamlit_dsfr/frontend/st_dsfr_default/_astro/DsfrInput.DziUIn1e.js
streamlit_dsfr/frontend/st_dsfr_default/_astro/DsfrPicture.CSxoY7wo.js
streamlit_dsfr/frontend/st_dsfr_default/_astro/DsfrRadioButtonSet.D-wXl8nu.js
streamlit_dsfr/frontend/st_dsfr_default/_astro/DsfrRange.Lj32ve8T.js
streamlit_dsfr/frontend/st_dsfr_default/_astro/Marianne-Bold.CYjThbH0.woff2
streamlit_dsfr/frontend/st_dsfr_default/_astro/Marianne-Bold.u6yfe4-h.woff
streamlit_dsfr/frontend/st_dsfr_default/_astro/Marianne-Bold_Italic.BWnPOpjP.woff
streamlit_dsfr/frontend/st_dsfr_default/_astro/Marianne-Bold_Italic.BqW9V1Nh.woff2
streamlit_dsfr/frontend/st_dsfr_default/_astro/Marianne-Light.DqWaxKdz.woff
streamlit_dsfr/frontend/st_dsfr_default/_astro/Marianne-Light.DsZfzyg9.woff2
streamlit_dsfr/frontend/st_dsfr_default/_astro/Marianne-Light_Italic.BJOCXSxu.woff
streamlit_dsfr/frontend/st_dsfr_default/_astro/Marianne-Light_Italic.Yne2G_jl.woff2
streamlit_dsfr-0.0.15.dist-info/METADATA
streamlit_dsfr-0.0.15.dist-info/WHEEL
streamlit_dsfr-0.0.15.dist-info/top_level.txt
streamlit_dsfr-0.0.15.dist-info/RECORD
